ravworks_exporter/__init__.py
ravworks_exporter/auth_hooks.py
ravworks_exporter/forms.py
ravworks_exporter/models.py
ravworks_exporter/urls.py
ravworks_exporter/views.py
ravworks_exporter/exporters/__init__.py
ravworks_exporter/exporters/skills/__init__.py
ravworks_exporter/exporters/skills/corptools.py
ravworks_exporter/exporters/skills/memberaudit.py
ravworks_exporter/exporters/skills/skill_settings.py
ravworks_exporter/exporters/structures/__init__.py
ravworks_exporter/exporters/structures/corptools.py
ravworks_exporter/exporters/structures/structures.py
ravworks_exporter/exporters/structures/structures_settings.py
ravworks_exporter/migrations/__init__.py
ravworks_exporter/templates/ravworks_exporter/index.html
aa_ravworks_exporter-0.5.1.dist-info/LICENSE
aa_ravworks_exporter-0.5.1.dist-info/WHEEL
aa_ravworks_exporter-0.5.1.dist-info/METADATA
aa_ravworks_exporter-0.5.1.dist-info/RECORD
